anuvaad/__init__.py
anuvaad/anuvaad.py
anuvaad-1.0.6.dist-info/LICENSE
anuvaad-1.0.6.dist-info/METADATA
anuvaad-1.0.6.dist-info/WHEEL
anuvaad-1.0.6.dist-info/top_level.txt
anuvaad-1.0.6.dist-info/RECORD
