Metadata-Version: 2.1
Name: anuvaad
Version: 1.0.6
Summary: State of the art translation for Indic languages.
Home-page: https://github.com/notAI-tech/Anuvaad
Author: BEDAPUDI PRANEETH
Author-email: praneeth@bpraneeth.com
License: GPLv3
Platform: UNKNOWN
Classifier: License :: OSI Approved :: GNU General Public License v3 (GPLv3)
Classifier: Programming Language :: Python
Classifier: Programming Language :: Python :: 3
Classifier: Programming Language :: Python :: 3.6
Classifier: Programming Language :: Python :: Implementation :: CPython
Classifier: Programming Language :: Python :: Implementation :: PyPy
Requires-Python: >=3.6.0
Requires-Dist: transformers (>=4.5.0)
Requires-Dist: pydload (>=1.0.9)
Requires-Dist: torch (>=1.5.0)
Requires-Dist: sentencepiece
